sliceri18n/__init__.py
sliceri18n/functions.py
sliceri18n/py.typed
sliceri18n/version.py
sliceri18n/functionspack/__init__.py
sliceri18n/functionspack/functions.py
sliceri18n-1.0.1.dist-info/LICENSE
sliceri18n-1.0.1.dist-info/METADATA
sliceri18n-1.0.1.dist-info/WHEEL
sliceri18n-1.0.1.dist-info/top_level.txt
sliceri18n-1.0.1.dist-info/RECORD
